mfid.py
mfid-1.0.0.dist-info/LICENSE
mfid-1.0.0.dist-info/METADATA
mfid-1.0.0.dist-info/WHEEL
mfid-1.0.0.dist-info/top_level.txt
mfid-1.0.0.dist-info/RECORD
