Metadata-Version: 2.2
Name: mfid
Version: 1.0.0
Summary: MFID: a Mighty Fine Identifier
Home-page: https://github.com/MolecularFoundry/mfid
Author: Edward S. Barnard
Author-email: esbarnard@lbl.gov
License: BSD
License-File: LICENSE
Requires-Dist: uuid7
Dynamic: author
Dynamic: author-email
Dynamic: description
Dynamic: description-content-type
Dynamic: home-page
Dynamic: license
Dynamic: requires-dist
Dynamic: summary
